DataHoarder/__init__.py
DataHoarder/main.py
datahoarder-0.0.2.dist-info/METADATA
datahoarder-0.0.2.dist-info/WHEEL
datahoarder-0.0.2.dist-info/RECORD
